solax/__init__.py
solax/discovery.py
solax/inverter.py
solax/inverter_http_client.py
solax/response_parser.py
solax/units.py
solax/utils.py
solax/inverters/__init__.py
solax/inverters/qvolt_hyb_g3_3p.py
solax/inverters/x1.py
solax/inverters/x1_boost.py
solax/inverters/x1_g4_series.py
solax/inverters/x1_hybrid_gen4.py
solax/inverters/x1_lite_lv.py
solax/inverters/x1_mini.py
solax/inverters/x1_mini_v34.py
solax/inverters/x1_smart.py
solax/inverters/x3.py
solax/inverters/x3_evc.py
solax/inverters/x3_hybrid_g4.py
solax/inverters/x3_mic_pro_g2.py
solax/inverters/x3_ultra.py
solax/inverters/x3_v34.py
solax/inverters/x_hybrid.py
solax-3.2.4.dist-info/licenses/LICENSE
solax-3.2.4.dist-info/METADATA
solax-3.2.4.dist-info/WHEEL
solax-3.2.4.dist-info/entry_points.txt
solax-3.2.4.dist-info/top_level.txt
solax-3.2.4.dist-info/RECORD
