Metadata-Version: 2.4
Name: solax
Version: 3.2.4
Summary: Solax inverter API client
Home-page: https://github.com/squishykid/solax
Author: Robin Wohlers-Reichel
Author-email: me@robinwr.com
License: MIT
Classifier: Programming Language :: Python :: 3
Classifier: License :: OSI Approved :: MIT License
Classifier: Operating System :: OS Independent
Requires-Python: >=3.8
License-File: LICENSE
Requires-Dist: aiohttp<4,>=3.5.4
Requires-Dist: voluptuous>=0.11.5
Requires-Dist: importlib_metadata>=3.6; python_version < "3.10"
Requires-Dist: typing_extensions>=4.1.0; python_version < "3.11"
Dynamic: author
Dynamic: author-email
Dynamic: classifier
Dynamic: description
Dynamic: description-content-type
Dynamic: home-page
Dynamic: license
Dynamic: license-file
Dynamic: requires-dist
Dynamic: requires-python
Dynamic: summary
